[
  {
    "region": "apac",
    "service": "support",
    "latency_ms": 174,
    "uptime_pct": 99.241,
    "timestamp": 20250301
  },
  {
    "region": "apac",
    "service": "support",
    "latency_ms": 209.9,
    "uptime_pct": 97.5,
    "timestamp": 20250302
  },
  {
    "region": "apac",
    "service": "payments",
    "latency_ms": 155.28,
    "uptime_pct": 99.318,
    "timestamp": 20250303
  },
  {
    "region": "apac",
    "service": "recommendations",
    "latency_ms": 186.74,
    "uptime_pct": 99.377,
    "timestamp": 20250304
  },
  {
    "region": "apac",
    "service": "recommendations",
    "latency_ms": 122.48,
    "uptime_pct": 99.322,
    "timestamp": 20250305
  },
  {
    "region": "apac",
    "service": "support",
    "latency_ms": 144.71,
    "uptime_pct": 99.219,
    "timestamp": 20250306
  },
  {
    "region": "apac",
    "service": "analytics",
    "latency_ms": 180.95,
    "uptime_pct": 97.69,
    "timestamp": 20250307
  },
  {
    "region": "apac",
    "service": "payments",
    "latency_ms": 198.38,
    "uptime_pct": 98.079,
    "timestamp": 20250308
  },
  {
    "region": "apac",
    "service": "payments",
    "latency_ms": 173.05,
    "uptime_pct": 97.479,
    "timestamp": 20250309
  },
  {
    "region": "apac",
    "service": "recommendations",
    "latency_ms": 176.61,
    "uptime_pct": 97.659,
    "timestamp": 20250310
  },
  {
    "region": "apac",
    "service": "payments",
    "latency_ms": 219.38,
    "uptime_pct": 98.368,
    "timestamp": 20250311
  },
  {
    "region": "apac",
    "service": "support",
    "latency_ms": 126.21,
    "uptime_pct": 97.448,
    "timestamp": 20250312
  },
  {
    "region": "emea",
    "service": "recommendations",
    "latency_ms": 211.28,
    "uptime_pct": 98.534,
    "timestamp": 20250301
  },
  {
    "region": "emea",
    "service": "checkout",
    "latency_ms": 137.93,
    "uptime_pct": 98.617,
    "timestamp": 20250302
  },
  {
    "region": "emea",
    "service": "checkout",
    "latency_ms": 148.49,
    "uptime_pct": 98.354,
    "timestamp": 20250303
  },
  {
    "region": "emea",
    "service": "support",
    "latency_ms": 221.11,
    "uptime_pct": 97.267,
    "timestamp": 20250304
  },
  {
    "region": "emea",
    "service": "support",
    "latency_ms": 123.22,
    "uptime_pct": 99.488,
    "timestamp": 20250305
  },
  {
    "region": "emea",
    "service": "recommendations",
    "latency_ms": 122.4,
    "uptime_pct": 97.701,
    "timestamp": 20250306
  },
  {
    "region": "emea",
    "service": "recommendations",
    "latency_ms": 180.09,
    "uptime_pct": 98.436,
    "timestamp": 20250307
  },
  {
    "region": "emea",
    "service": "recommendations",
    "latency_ms": 166.29,
    "uptime_pct": 98.006,
    "timestamp": 20250308
  },
  {
    "region": "emea",
    "service": "catalog",
    "latency_ms": 177.65,
    "uptime_pct": 98.979,
    "timestamp": 20250309
  },
  {
    "region": "emea",
    "service": "checkout",
    "latency_ms": 181.03,
    "uptime_pct": 98.44,
    "timestamp": 20250310
  },
  {
    "region": "emea",
    "service": "payments",
    "latency_ms": 221.55,
    "uptime_pct": 98.803,
    "timestamp": 20250311
  },
  {
    "region": "emea",
    "service": "catalog",
    "latency_ms": 214.31,
    "uptime_pct": 97.191,
    "timestamp": 20250312
  },
  {
    "region": "amer",
    "service": "catalog",
    "latency_ms": 210.12,
    "uptime_pct": 99.216,
    "timestamp": 20250301
  },
  {
    "region": "amer",
    "service": "recommendations",
    "latency_ms": 230.83,
    "uptime_pct": 98.334,
    "timestamp": 20250302
  },
  {
    "region": "amer",
    "service": "payments",
    "latency_ms": 131.4,
    "uptime_pct": 98.879,
    "timestamp": 20250303
  },
  {
    "region": "amer",
    "service": "checkout",
    "latency_ms": 154.88,
    "uptime_pct": 97.469,
    "timestamp": 20250304
  },
  {
    "region": "amer",
    "service": "payments",
    "latency_ms": 166.55,
    "uptime_pct": 98.219,
    "timestamp": 20250305
  },
  {
    "region": "amer",
    "service": "checkout",
    "latency_ms": 220.74,
    "uptime_pct": 97.313,
    "timestamp": 20250306
  },
  {
    "region": "amer",
    "service": "support",
    "latency_ms": 171,
    "uptime_pct": 99.309,
    "timestamp": 20250307
  },
  {
    "region": "amer",
    "service": "recommendations",
    "latency_ms": 232.6,
    "uptime_pct": 97.147,
    "timestamp": 20250308
  },
  {
    "region": "amer",
    "service": "payments",
    "latency_ms": 127.05,
    "uptime_pct": 98.736,
    "timestamp": 20250309
  },
  {
    "region": "amer",
    "service": "payments",
    "latency_ms": 184.29,
    "uptime_pct": 97.731,
    "timestamp": 20250310
  },
  {
    "region": "amer",
    "service": "analytics",
    "latency_ms": 133.6,
    "uptime_pct": 98.161,
    "timestamp": 20250311
  },
  {
    "region": "amer",
    "service": "payments",
    "latency_ms": 193.13,
    "uptime_pct": 97.997,
    "timestamp": 20250312
  }
]
